mohand_plugin_expect/__init__.py
mohand_plugin_expect/hand.py
mohand_plugin_expect/main.py
mohand_plugin_expect/version.py
mohand_plugin_expect-1.0.6.dist-info/METADATA
mohand_plugin_expect-1.0.6.dist-info/RECORD
mohand_plugin_expect-1.0.6.dist-info/WHEEL
mohand_plugin_expect-1.0.6.dist-info/entry_points.txt
mohand_plugin_expect-1.0.6.dist-info/top_level.txt
